ytmusic_deleter-3.5.2.dist-info/METADATA
ytmusic_deleter-3.5.2.dist-info/WHEEL
ytmusic_deleter-3.5.2.dist-info/entry_points.txt
ytmusic_deleter-3.5.2.dist-info/licenses/LICENSE
ytmusic_deleter/_version.py
ytmusic_deleter/auth.py
ytmusic_deleter/cli.py
ytmusic_deleter/common.py
ytmusic_deleter/duplicates.py
ytmusic_deleter/progress.py
ytmusic_deleter/uploads.py
ytmusic_deleter-3.5.2.dist-info/RECORD
