Metadata-Version: 2.1
Name: ytmusic-deleter
Version: 3.5.2
Summary: Easily delete your YouTube Music library
Author-Email: apastel <alex.r.pastel@gmail.com>
License: GPL-3.0
Requires-Python: >=3.10
Requires-Dist: click>=8.3.1
Requires-Dist: enlighten>=1.14.1
Requires-Dist: thefuzz>=0.22.1
Requires-Dist: ytmusicapi>=1.11.4
Requires-Dist: inquirerpy>=0.3.4
